odoo/addons/account_payment_auto_partner_bank/__init__.py
odoo/addons/account_payment_auto_partner_bank/__manifest__.py
odoo/addons/account_payment_auto_partner_bank/models/__init__.py
odoo/addons/account_payment_auto_partner_bank/models/account_invoice.py
odoo12_addon_account_payment_auto_partner_bank-12.0.1.0.1.dist-info/METADATA
odoo12_addon_account_payment_auto_partner_bank-12.0.1.0.1.dist-info/WHEEL
odoo12_addon_account_payment_auto_partner_bank-12.0.1.0.1.dist-info/top_level.txt
odoo12_addon_account_payment_auto_partner_bank-12.0.1.0.1.dist-info/RECORD
